Workbook

Sheet Dashboard
A2: THE BLACK ARROW COMPANY
A4: COMPREHENSIVE ACCOUNTING SYSTEM
A7: QUICK LINKS TO SHEETS
A8: 1. Revenue | B8: Enter all customer invoices and payments
A9: 2. Project Costing | B9: Track PO values, costs, and balances
A10: 3. Expenses | B10: Record all business expenses
A11: 4. VAT Management | B11: Track VAT in and out, manage VAT balance
A12: 5. Statement of Account | B12: P&L statement with all linked values
A13: 6. Partner Distribution | B13: Final shares for all 6 partners
A17: COMPANY INFORMATION
A18: Company Name: | B18: The Black Arrow Company
A19: Country: | B19: Saudi Arabia
A20: Currency: | B20: Saudi Riyal (SAR)
A21: Tax Rate (VAT): | B21: 15%
A22: Year: | B22: 2026
A26: PARTNER SHAREHOLDING
A27: Adnan Afzal | B27: 0.17
A28: Zain Humayoun | B28: 0.17
A29: Talha Ansari | B29: 0.17
A30: Asad Rehman | B30: 0.17
A31: Shahzad Khan | B31: 0.17
A32: Yousuf | B32: 0.075

Sheet Revenue
A1: THE BLACK ARROW COMPANY
A2: REVENUE TRACKING
A3: As of 30 May 2026
A5: Entry# | B5: Date | C5: Customer Name | D5: Invoice # | E5: Gross Amount (SAR) | F5: VAT Amount | G5: Net Amount | H5: Notes
A6: 1 | F6: =E6*0.15 | G6: =E6-F6
A7: 2 | F7: =E7*0.15 | G7: =E7-F7
A8: 3 | F8: =E8*0.15 | G8: =E8-F8
A9: 4 | F9: =E9*0.15 | G9: =E9-F9
A10: 5 | F10: =E10*0.15 | G10: =E10-F10
A11: 6 | F11: =E11*0.15 | G11: =E11-F11
A12: 7 | F12: =E12*0.15 | G12: =E12-F12
A13: 8 | F13: =E13*0.15 | G13: =E13-F13
A14: 9 | F14: =E14*0.15 | G14: =E14-F14
A15: 10 | F15: =E15*0.15 | G15: =E15-F15
A16: 11 | F16: =E16*0.15 | G16: =E16-F16
A17: 12 | F17: =E17*0.15 | G17: =E17-F17
... A35: 30 | F35: =E35*0.15 | G35: =E35-F35
A37: TOTAL REVENUE | E37: =SUM(E5:E34) | F37: =SUM(F5:F34) | G37: =SUM(G5:G34)

Sheet Project Costing
A1: THE BLACK ARROW COMPANY
A2: PROJECT COSTING - PO TRACKING
A3: As of 30 May 2026
A5: Entry# | B5: Date | C5: Project Name | D5: PO # | E5: PO Value (SAR) | F5: Cost Paid (SAR) | G5: Balance (SAR) | H5: Notes
A6: 1 | G6: =E6-F6
A7: 2 | G7: =E7-F7
A8: 3 | G8: =E8-F8
A9: 4 | G9: =E9-F9
A10: 5 | G10: =E10-F10
A11: 6 | G11: =E11-F11
A12: 7 | G12: =E12-F12
A13: 8 | G13: =E13-F13
A14: 9 | G14: =E14-F14
A15: 10 | G15: =E15-F15
A16: 11 | G16: =E16-F16
A17: 12 | G17: =E17-F17
... A30: 25 | G30: =E30-F30
A32: TOTALS | E32: =SUM(E5:E29) | F32: =SUM(F5:F29) | G32: =SUM(G5:G29)

Sheet Expenses
A1: THE BLACK ARROW COMPANY
A2: OPERATING EXPENSES
A3: As of 30 May 2026
A5: Entry# | B5: Date | C5: Expense Category | D5: Amount (SAR) | E5: VAT Recoverable | F5: Invoice # | G5: Notes
A6: 1
A7: 2
A8: 3
A9: 4
A10: 5
A11: 6
A12: 7
A13: 8
A14: 9
A15: 10
A16: 11
A17: 12
... A30: 25
A32: TOTAL EXPENSES | D32: =SUM(D5:D29)

Sheet VAT Management
A1: THE BLACK ARROW COMPANY
A2: VAT MANAGEMENT & RECONCILIATION
A3: As of 30 May 2026
A6: VAT COLLECTED FROM CUSTOMERS (Output VAT)
A7: Description | B7: Gross Amount | C7: VAT @ 15% | D7: Reference
A8: Total Revenue from Revenue Sheet | B8: =Revenue!E35 | C8: =Revenue!F35 | D8: From Revenue Sheet
A11: VAT PAID ON EXPENSES (Input VAT)
A12: Description | B12: Expense Amount | C12: VAT @ 15% | D12: Reference
A13: Total Expenses from Expenses Sheet | B13: =Expenses!D30 | C13: =B13*0.15 | D13: From Expenses Sheet
A16: VAT RECONCILIATION SUMMARY
A17: VAT Collected from Customers | B17: =C8
A18: Less: VAT Paid on Expenses | B18: =C13
A19: NET VAT LIABILITY / (REFUND) | B19: =B17-B18
A21: Note: Positive amount = VAT payable to authorities

Sheet Statement of Account
A1: THE BLACK ARROW COMPANY
A2: STATEMENT OF ACCOUNT (P&L)
A3: As of 30 May 2026
A5: STATEMENT OF PROFIT & LOSS
A6: Description | B6: Amount (SAR) | C6: Variance
A7: REVENUE
A8: Gross Sales | B8: =Revenue!E35
A9: Less: VAT on Sales | B9: =Revenue!F35
A10: NET REVENUE | B10: =B8-B9
A12: COSTS
A13: Project Costs | B13: ='Project Costing'!F29
A14: Operating Expenses | B14: =Expenses!D30
A15: TOTAL COSTS | B15: =B13+B14
A17: GROSS PROFIT / (LOSS) | B17: =B10-B15

Sheet Partner Distribution
A1: THE BLACK ARROW COMPANY
A2: PARTNER PROFIT DISTRIBUTION
A3: As of 30 May 2026
A5: Partner Name | B5: Shareholding % | C5: Share of Profit (SAR) | D5: Notes
A6: Adnan Afzal | B6: 0.17 | C6: ='Statement of Account'!B17*B6 | D6: Based on 17.0% shareholding
A7: Zain Humayoun | B7: 0.17 | C7: ='Statement of Account'!B17*B7 | D7: Based on 17.0% shareholding
A8: Talha Ansari | B8: 0.17 | C8: ='Statement of Account'!B17*B8 | D8: Based on 17.0% shareholding
A9: Asad Rehman | B9: 0.17 | C9: ='Statement of Account'!B17*B9 | D9: Based on 17.0% shareholding
A10: Shahzad Khan | B10: 0.17 | C10: ='Statement of Account'!B17*B10 | D10: Based on 17.0% shareholding
A11: Yousuf | B11: 0.075 | C11: ='Statement of Account'!B17*B11 | D11: Based on 7.5% shareholding
A13: TOTAL DISTRIBUTION | C13: ='Statement of Account'!B17

Sheet Instructions
A2: THE BLACK ARROW COMPANY - ACCOUNTING SYSTEM USER GUIDE
A5: SYSTEM OVERVIEW
A6: This comprehensive accounting system tracks all company financial activities and automatically generates financial statements and partner distribution reports.
A8: SHEETS & THEIR PURPOSE
A9: 1. DASHBOARD Navigation hub and company information overview
A10: 2. REVENUE Record all customer invoices and payment collections. VAT is automatically calculated at 15%.
A11: 3. PROJECT COSTING Track Purchase Orders (PO), budgeted amounts, actual costs paid, and remaining balances.
A12: 4. EXPENSES Log all operating expenses (rent, utilities, salaries, professional fees, etc.)
A13: 5. VAT MANAGEMENT Automatic reconciliation of:
A14: • VAT collected from customers (Output VAT)
A15: • VAT paid on expenses (Input VAT)
A16: • Net VAT liability or refund due
... A71: For questions about data entry, refer to the specific sheet headers and examples provided in each sheet.
